cujirax/__init__.py
cujirax/cucumber.py
cujirax/jira.py
cujirax/xray/__init__.py
cujirax/xray/graphql.py
cujirax/xray/import_results.py
cujirax/xray/import_tests.py
cujirax-0.8.1.dist-info/LICENSE
cujirax-0.8.1.dist-info/WHEEL
cujirax-0.8.1.dist-info/METADATA
cujirax-0.8.1.dist-info/RECORD
