Metadata-Version: 2.1
Name: cujirax
Version: 0.8.1
Summary: Cucumber result to Jira Xray Test repository
Author-email: Max Leow <maxengiu@outlook.com>
Classifier: License :: OSI Approved :: MIT License
Requires-Dist: pydantic==1.10.10
Requires-Dist: atlassian-python-api
Requires-Dist: requests
Requires-Dist: loguru
Requires-Dist: jinja2
Requires-Dist: graphqlclient
Project-URL: Home, https://github.com/maxleow/cujirax
